sftp_uploader/__init__.py
sftp_uploader/applications/__init__.py
sftp_uploader/applications/dependency_container.py
sftp_uploader/applications/env_load.py
sftp_uploader/applications/git_manipulation.py
sftp_uploader/applications/logs.py
sftp_uploader/applications/pre_commit_actions.py
sftp_uploader/applications/sftp.py
sftp_uploader/applications/sftp_uploader.py
sftp_uploader/applications/ssh.py
sftp_uploader/constants/applications/dependency_container.py
sftp_uploader/constants/applications/env_load.py
sftp_uploader/constants/applications/git_manipulation.py
sftp_uploader/constants/applications/logs.py
sftp_uploader/constants/applications/ssh.py
sftp_uploader/script_to_setup_package.py
sftp_uploader/services/__init__.py
sftp_uploader/services/applications/git_manipulation.py
sftp_uploader/services/applications/sftp_uploader.py
sftp_uploader/services/exceptions/pre_commit_actions.py
sftp_uploader/services/exceptions/sftp.py
sftp_uploader/services/exceptions/ssh.py
sftp_uploader-1.0.16.dist-info/LICENSE
sftp_uploader-1.0.16.dist-info/WHEEL
sftp_uploader-1.0.16.dist-info/entry_points.txt
sftp_uploader-1.0.16.dist-info/METADATA
sftp_uploader-1.0.16.dist-info/RECORD
